django_vouch_proxy_auth/__init__.py
django_vouch_proxy_auth/backends.py
django_vouch_proxy_auth/middleware.py
django_vouch_proxy_auth-0.1.3.dist-info/LICENSE
django_vouch_proxy_auth-0.1.3.dist-info/METADATA
django_vouch_proxy_auth-0.1.3.dist-info/WHEEL
django_vouch_proxy_auth-0.1.3.dist-info/top_level.txt
django_vouch_proxy_auth-0.1.3.dist-info/RECORD
