Metadata-Version: 2.1
Name: django-vouch-proxy-auth
Version: 0.1.3
Summary: Django Middleware to enable SSO using Vouch Proxy
Home-page: https://github.com/bdalpe/django-vouch-proxy-auth
Author: Brendan Dalpe
Author-email: bdalpe@gmail.com
License: MIT
Keywords: sso,django,vouch
Platform: UNKNOWN
Classifier: Development Status :: 5 - Production/Stable
Classifier: Intended Audience :: Developers
Classifier: Natural Language :: English
Classifier: License :: OSI Approved :: MIT License
Classifier: Programming Language :: Python
Classifier: Programming Language :: Python :: 3
Classifier: Programming Language :: Python :: 3 :: Only
Classifier: Programming Language :: Python :: 3.6
Classifier: Programming Language :: Python :: 3.7
Classifier: Programming Language :: Python :: 3.8
Classifier: Programming Language :: Python :: 3.9
Classifier: Topic :: Utilities
Classifier: Framework :: Django
Classifier: Framework :: Django :: 2.2
Classifier: Framework :: Django :: 3.0
Classifier: Framework :: Django :: 3.1
Requires-Python: >=3.6
Requires-Dist: PyJWT (>=2.0.0)
Requires-Dist: requests (>=2.0.0)
